setup.py
uddin_probability/Binomialdistribution.py
uddin_probability/Gaussiandistribution.py
uddin_probability/Generaldistribution.py
uddin_probability/__init__.py
uddin_probability.egg-info/PKG-INFO
uddin_probability.egg-info/SOURCES.txt
uddin_probability.egg-info/dependency_links.txt
uddin_probability.egg-info/not-zip-safe
uddin_probability.egg-info/top_level.txt