Metadata-Version: 1.0
Name: uddin-probability
Version: 0.1
Summary: Gaussian and Binomial distributions
Home-page: UNKNOWN
Author: Md Salah Uddin
Author-email: sajitsalahuddin@live.com
License: UNKNOWN
Platform: UNKNOWN
